.gitignore
COPYING
Makefile
README.md
TODO
setup.py
doc/index.html
samples/rest2pdf/README
samples/rest2pdf/rest2pdf.py
samples/rest2pdf/rst.txt
samples/wiki2pdf/README
samples/wiki2pdf/wiki2pdf.py
src/pypdflib/__init__.py
src/pypdflib/styles.py
src/pypdflib/widgets.py
src/pypdflib/writer.py
src/pypdflib.egg-info/PKG-INFO
src/pypdflib.egg-info/SOURCES.txt
src/pypdflib.egg-info/dependency_links.txt
src/pypdflib.egg-info/namespace_packages.txt
src/pypdflib.egg-info/not-zip-safe
src/pypdflib.egg-info/requires.txt
src/pypdflib.egg-info/top_level.txt
src/pypdflib/utils/__init__.py
src/pypdflib/utils/normalizer.py
src/pypdflib/utils/hyphenation/__init__.py
src/pypdflib/utils/hyphenation/hyphenator.py
src/pypdflib/utils/hyphenation/rules/README
src/pypdflib/utils/hyphenation/rules/hyph_as_IN.dic
src/pypdflib/utils/hyphenation/rules/hyph_bn_IN.dic
src/pypdflib/utils/hyphenation/rules/hyph_en_US.dic
src/pypdflib/utils/hyphenation/rules/hyph_gu_IN.dic
src/pypdflib/utils/hyphenation/rules/hyph_hi_IN.dic
src/pypdflib/utils/hyphenation/rules/hyph_kn_IN.dic
src/pypdflib/utils/hyphenation/rules/hyph_ml_IN.dic
src/pypdflib/utils/hyphenation/rules/hyph_mr_IN.dic
src/pypdflib/utils/hyphenation/rules/hyph_or_IN.dic
src/pypdflib/utils/hyphenation/rules/hyph_pa_IN.dic
src/pypdflib/utils/hyphenation/rules/hyph_ta_IN.dic
src/pypdflib/utils/hyphenation/rules/hyph_te_IN.dic
tests/CC-BY-SA-3.0.txt
tests/README
tests/White_peacock.jpg
tests/arabic.txt
tests/bengali.txt
tests/hindi.txt
tests/image_test.py
tests/japanese.txt
tests/kannada.txt
tests/malayalam.txt
tests/scripts.pdf
tests/scripts_test.py
tests/tamil.txt