Metadata-Version: 1.0
Name: pypdflib
Version: 0.1.a3
Summary: PangoCairo based Python PDF Library
Home-page: https://savannah.nongnu.org/projects/pypdflib
Author: Santhosh Thottingal
Author-email: santhosh.thottingal@gmail.com
License: LGPL 3.0
Platform: UNKNOWN
